seedlayer/__init__.py
seedlayer/py.typed
seedlayer/seedlayer.py
seedlayer-0.1.0.dist-info/WHEEL
seedlayer-0.1.0.dist-info/METADATA
seedlayer-0.1.0.dist-info/RECORD
