Metadata-Version: 2.3
Name: seedlayer
Version: 0.1.0
Summary: Deterministic DB seeding for SQLAlchemy
Author: François Naggar-Tremblay
Author-email: François Naggar-Tremblay <francois.n.tremblay@gmail.com>
Requires-Dist: sqlalchemy>=2.0
Requires-Dist: faker>=37.5.3
Requires-Dist: pytest>=8.4.1 ; extra == 'dev'
Requires-Dist: ruff==0.12.10 ; extra == 'dev'
Requires-Dist: seedlayer ; extra == 'dev'
Requires-Dist: pytest-cov==6.2.1 ; extra == 'dev'
Requires-Python: >=3.11
Provides-Extra: dev
